CHANGES.txt
README.txt
setup.py
corejet/__init__.py
corejet.jira.egg-info/PKG-INFO
corejet.jira.egg-info/SOURCES.txt
corejet.jira.egg-info/dependency_links.txt
corejet.jira.egg-info/entry_points.txt
corejet.jira.egg-info/namespace_packages.txt
corejet.jira.egg-info/not-zip-safe
corejet.jira.egg-info/requires.txt
corejet.jira.egg-info/top_level.txt
corejet/jira/__init__.py
corejet/jira/source.py