Metadata-Version: 1.0
Name: corejet.jira
Version: 1.0a3
Summary: JIRA data source for corejet.testrunner
Home-page: http://corejet.org
Author: Martin Aspeli
Author-email: optilude@gmail.com
License: ZPL 2.1
Keywords: corejet JIRA
Platform: UNKNOWN
Classifier: Programming Language :: Python
